odoo/addons/stock_production_lot_traceability_shipment_report/README.rst
odoo/addons/stock_production_lot_traceability_shipment_report/__init__.py
odoo/addons/stock_production_lot_traceability_shipment_report/__manifest__.py
odoo/addons/stock_production_lot_traceability_shipment_report/i18n/stock_production_lot_traceability_shipment_report.pot
odoo/addons/stock_production_lot_traceability_shipment_report/readme/CONTRIBUTORS.rst
odoo/addons/stock_production_lot_traceability_shipment_report/readme/DESCRIPTION.rst
odoo/addons/stock_production_lot_traceability_shipment_report/readme/USAGE.rst
odoo/addons/stock_production_lot_traceability_shipment_report/reports/__init__.py
odoo/addons/stock_production_lot_traceability_shipment_report/reports/stock_shipment_traceability_report.py
odoo/addons/stock_production_lot_traceability_shipment_report/reports/stock_shipment_traceability_report.xml
odoo/addons/stock_production_lot_traceability_shipment_report/security/ir.model.access.csv
odoo/addons/stock_production_lot_traceability_shipment_report/security/security.xml
odoo/addons/stock_production_lot_traceability_shipment_report/static/description/icon.png
odoo/addons/stock_production_lot_traceability_shipment_report/static/description/index.html
odoo/addons/stock_production_lot_traceability_shipment_report/tests/__init__.py
odoo/addons/stock_production_lot_traceability_shipment_report/tests/test_stock_shipment_report.py
odoo/addons/stock_production_lot_traceability_shipment_report/wizards/__init__.py
odoo/addons/stock_production_lot_traceability_shipment_report/wizards/stock_shipment_traceability_report_wizard.py
odoo/addons/stock_production_lot_traceability_shipment_report/wizards/stock_shipment_traceability_report_wizard.xml
odoo12_addon_stock_production_lot_traceability_shipment_report-12.0.1.0.1.dist-info/METADATA
odoo12_addon_stock_production_lot_traceability_shipment_report-12.0.1.0.1.dist-info/WHEEL
odoo12_addon_stock_production_lot_traceability_shipment_report-12.0.1.0.1.dist-info/top_level.txt
odoo12_addon_stock_production_lot_traceability_shipment_report-12.0.1.0.1.dist-info/RECORD
